django_gamification/__init__.py
django_gamification/models.py
django_gamification/signals.py
django_gamification/migrations/0001_initial.py
django_gamification/migrations/0002_auto_20170822_1011.py
django_gamification/migrations/0003_pointchange.py
django_gamification/migrations/0004_badge_points.py
django_gamification/migrations/0005_auto_20170907_1058.py
django_gamification/migrations/0006_auto_20170907_1317.py
django_gamification/migrations/0007_auto_20170908_1044.py
django_gamification/migrations/0008_remove_badge_next_badge.py
django_gamification/migrations/0009_auto_20171002_0803.py
django_gamification/migrations/0010_badge_revoked.py
django_gamification/migrations/0011_auto_20171006_0744.py
django_gamification/migrations/0012_auto_20171006_0759.py
django_gamification/migrations/0013_auto_20180324_0605.py
django_gamification/migrations/__init__.py
django_gamification-0.3.2.dist-info/DESCRIPTION.rst
django_gamification-0.3.2.dist-info/METADATA
django_gamification-0.3.2.dist-info/RECORD
django_gamification-0.3.2.dist-info/WHEEL
django_gamification-0.3.2.dist-info/metadata.json
django_gamification-0.3.2.dist-info/top_level.txt
